{"is_source_file": true, "format": "bash", "description": "A shell script for detecting and backing up various database systems (SQLite, PostgreSQL, MySQL, MongoDB). It performs checks for the presence and activity of each database type and executes the appropriate backup commands, exporting backups to specific files.", "external_files": ["/usr/lib/postgresql/", "/var/run/mysqld/mysqld.sock"], "external_methods": ["ls", "cp", "sudo", "mysqladmin", "mysql", "mysqldump", "mongosh", "mongodump", "echo", "exit"], "published": [], "classes": [], "methods": [], "calls": ["ls /usr/lib/postgresql/", "cp \"${DB_NAME}\" \"database_backup.db\"", "sudo -u postgres ${PG_BIN}/pg_isready", "mysqladmin ping -h localhost -P ${DB_PORT} --silent", "sudo mysqladmin ping --socket=/var/run/mysqld/mysqld.sock --silent", "mysql -h localhost -P ${DB_PORT} -u ${DB_USER} -p${DB_PASSWORD} -e \"SELECT 1\"", "mysqldump -h localhost -P ${DB_PORT} -u ${DB_USER} -p${DB_PASSWORD} --databases ${DB_NAME} --add-drop-database --routines --triggers --single-transaction", "mongosh --port ${DB_PORT} --eval \"db.adminCommand('ping')\"", "mongodump --port ${DB_PORT} --db ${DB_NAME} --archive=database_backup.archive --quiet"], "search-terms": ["backup", "SQLite", "PostgreSQL", "MySQL", "MongoDB", "database_backup", "database", "shell script", "database detection", "cross-database backup"], "state": 2, "file_id": 8, "knowledge_revision": 18, "git_revision": "9a0ac62024b2be1b7ea217e481ca87e15a7d4d16", "hash": "d7da372b768c895a33088027314656c3", "format-version": 4, "code-base-name": "tic_tac_toe_database", "filename": "tic_tac_toe_database/backup_db.sh", "revision_history": [{"18": "9a0ac62024b2be1b7ea217e481ca87e15a7d4d16"}]}